godot_build/__init__.py
godot_build/config.py
godot_build/gdbuild.py
godot_build/godot.py
godot_build-0.1.2.dist-info/METADATA
godot_build-0.1.2.dist-info/WHEEL
godot_build-0.1.2.dist-info/entry_points.txt
godot_build-0.1.2.dist-info/top_level.txt
godot_build-0.1.2.dist-info/RECORD
