Metadata-Version: 2.1
Name: godot-build
Version: 0.1.2
Summary: Build tool for Godot projects.
Home-page: https://codeberg.org/Denotatum/gdbuild
Author: snegg21
Author-email: itsveter@gmail.com
License: GPL-3.0
Project-URL: Bug Reports, https://codeberg.org/Denotatum/gdbuild/issues
Project-URL: Source, https://codeberg.org/Denotatum/gdbuild
Keywords: godot
Classifier: Development Status :: 4 - Beta
Classifier: Operating System :: Unix
Classifier: Environment :: Console
Classifier: Intended Audience :: Developers
Classifier: Programming Language :: Python
Classifier: Programming Language :: Python :: 3
Classifier: Programming Language :: Python :: Implementation :: CPython
Classifier: License :: OSI Approved :: GNU General Public License v3 (GPLv3)
Classifier: Topic :: Utilities
Classifier: Topic :: Software Development
Requires-Python: >=3.6
